blackboxml/__init__.py
blackboxml/autopilot.py
blackboxml/visualiser.py
blackboxml-0.2.0.dist-info/licenses/LICENSE
blackboxml-0.2.0.dist-info/METADATA
blackboxml-0.2.0.dist-info/WHEEL
blackboxml-0.2.0.dist-info/top_level.txt
blackboxml-0.2.0.dist-info/RECORD
